ArpWitch/__init__.py
ArpWitch/__name__.py
ArpWitch/__version__.py
ArpWitch/datafile.py
ArpWitch/exec.py
ArpWitch/logger.py
ArpWitch/main.py
ArpWitch/sniffer.py
ArpWitch/utils.py
ArpWitch/witch.py
arpwitch/ArpWitch.py
arpwitch/LoggerManager.py
arpwitch/__init__.py
arpwitch/arp_witch.py
arpwitch/cli/__init__.py
arpwitch/cli/entrypoints.py
arpwitch/exceptions/ArpWitchException.py
arpwitch/exceptions/__init__.py
arpwitch/utils/__init__.py
arpwitch/utils/datafile.py
arpwitch/utils/exe.py
arpwitch/utils/logger.py
arpwitch/utils/sniffer.py
arpwitch/utils/utils.py
arpwitch/utils/witch.py
tests/__init__.py
tests/test_trivial.py
arpwitch-0.3.10.dist-info/LICENSE
arpwitch-0.3.10.dist-info/METADATA
arpwitch-0.3.10.dist-info/WHEEL
arpwitch-0.3.10.dist-info/entry_points.txt
arpwitch-0.3.10.dist-info/top_level.txt
arpwitch-0.3.10.dist-info/zip-safe
arpwitch-0.3.10.dist-info/RECORD
