Metadata-Version: 2.1
Name: arpwitch
Version: 0.3.10
Summary: A modern arpwatch replacement with JSON formatted outputs and easy options to exec commands when network changes are observed.
Home-page: https://arpwitch.readthedocs.io/
Author: Nicholas de Jong
Author-email: contact@nicholasdejong.com
License: BSD2
Keywords: arpwitch,arpwatch,arp,network,security
Platform: UNKNOWN
Classifier: Environment :: Console
Classifier: Intended Audience :: System Administrators
Classifier: Intended Audience :: Information Technology
Classifier: Topic :: System :: Networking :: Monitoring
Classifier: Programming Language :: Python :: 3
Classifier: License :: OSI Approved :: BSD License
Requires-Python: >=3.6.0,<4.0.0
License-File: LICENSE
Requires-Dist: scapy[basic]
Requires-Dist: psutil
Requires-Dist: ouilookup
